bagz.cpython-312-x86_64-linux-gnu.so
bagz.pyi
bagz.libs/libbrotlicommon-13786ce3.so.1.1.0
bagz.libs/libbrotlidec-651ea999.so.1.1.0
bagz.libs/libcom_err-70608b40.so.2.1
bagz.libs/libcrypto-143c618b.so.3
bagz.libs/libcurl-6a47146a.so.4.8.0
bagz.libs/libffi-6d66cdb3.so.8.1.4
bagz.libs/libgmp-71768353.so.10.5.0
bagz.libs/libgnutls-54a81713.so.30.40.3
bagz.libs/libgssapi_krb5-92a2cfac.so.2.2
bagz.libs/libhogweed-ff5f0620.so.6.10
bagz.libs/libidn2-e43ef30a.so.0.4.0
bagz.libs/libk5crypto-9316e985.so.3.1
bagz.libs/libkeyutils-532a5523.so.1.10
bagz.libs/libkrb5-44e95bad.so.3.3
bagz.libs/libkrb5support-772f1f7c.so.0.1
bagz.libs/liblber-2-4eee2020.5.so.0.1.14
bagz.libs/libldap-2-5f482155.5.so.0.1.14
bagz.libs/libnettle-63f06e70.so.8.10
bagz.libs/libnghttp2-b6186ebd.so.14.28.3
bagz.libs/libnghttp3-691fc280.so.9.2.6
bagz.libs/libp11-kit-112d5904.so.0.4.1
bagz.libs/libpsl-dcabd02c.so.5.3.4
bagz.libs/librtmp-e60809c3.so.1
bagz.libs/libsasl2-bc12d9a4.so.2.0.25
bagz.libs/libssh2-c2f01209.so.1.0.1
bagz.libs/libssl-2566cbef.so.3
bagz.libs/libtasn1-465fca63.so.6.6.4
bagz.libs/libunistring-8e2822e1.so.5.2.0
bagz.libs/libzstd-248fb04d.so.1.5.7
bagz-0.1.0.dist-info/METADATA
bagz-0.1.0.dist-info/WHEEL
bagz-0.1.0.dist-info/RECORD
bagz-0.1.0.dist-info/licenses/LICENSE
