Metadata-Version: 2.2
Name: bagz
Version: 0.1.0
Summary: A format for storing a sequence of byte-array records
Author-Email: Charlie Beattie <cbeattie@google.com>, =?utf-8?q?Augustin_=C5=BD=C3=ADdek?= <augustinzidek@google.com>, Nicolas Porcel <nicolasporcel@google.com>
License: 
Classifier: Development Status :: 5 - Production/Stable
Classifier: Intended Audience :: Developers
Classifier: License :: OSI Approved :: Apache Software License
Classifier: Operating System :: POSIX :: Linux
Classifier: Programming Language :: Python :: 3
Classifier: Programming Language :: Python :: 3.10
Classifier: Programming Language :: Python :: 3.11
Classifier: Programming Language :: Python :: 3.12
Classifier: Programming Language :: Python :: 3.13
Classifier: Programming Language :: Python :: 3 :: Only
Classifier: Topic :: Software Development :: Libraries :: Python Modules
Classifier: Topic :: File Formats
Classifier: Topic :: Scientific/Engineering
Project-URL: Homepage, https://github.com/google-deepmind/bagz
Project-URL: Bug Tracker, https://github.com/google-deepmind/bagz/issues
Requires-Python: <3.14,>=3.10
